{
	"animations": [
		{
			"offsets": [
				540,
				268
			],
			"loop": false,
			"fps": 24,
			"anim": "singLEFT",
			"indices": [],
			"name": "DV left"
		},
		{
			"offsets": [
				650,
				300
			],
			"loop": false,
			"fps": 24,
			"anim": "singDOWN",
			"indices": [],
			"name": "DV down"
		},
		{
			"offsets": [
				270,
				645
			],
			"loop": false,
			"fps": 24,
			"anim": "singUP",
			"indices": [],
			"name": "DV up"
		},
		{
			"offsets": [
				-87,
				229
			],
			"loop": false,
			"fps": 24,
			"anim": "singRIGHT",
			"indices": [],
			"name": "DV right"
		},
		{
			"offsets": [
				0,
				0
			],
			"indices": [],
			"fps": 24,
			"anim": "idle",
			"loop": true,
			"name": "DV idle"
		}
	],
	"no_antialiasing": false,
	"image": "characters/dv phase 2",
	"position": [
		120,
		-30
	],
	"healthicon": "dv",
	"flip_x": false,
	"healthbar_colors": [
		29,
		134,
		21
	],
	"camera_position": [
		-590,
		-300
	],
	"sing_duration": 6.1,
	"scale": 1.3
}