{
	"animations": [
		{
			"offsets": [
				0,
				0
			],
			"loop": false,
			"fps": 24,
			"anim": "idle",
			"indices": [],
			"name": "marco idle"
		},
		{
			"loop": false,
			"offsets": [
				84,
				15
			],
			"anim": "singLEFT",
			"fps": 24,
			"name": "marco right",
			"indices": []
		},
		{
			"loop": false,
			"offsets": [
				43,
				-130
			],
			"anim": "singUP",
			"fps": 24,
			"name": "marco down",
			"indices": []
		},
		{
			"loop": false,
			"offsets": [
				150,
				85
			],
			"anim": "singRIGHT",
			"fps": 24,
			"name": "marco left",
			"indices": []
		},
		{
			"offsets": [
				155,
				229
			],
			"indices": [
				0,
				1,
				2,
				3,
				4,
				5,
				6,
				7,
				8,
				8,
				8
			],
			"fps": 24,
			"anim": "singDOWN",
			"loop": false,
			"name": "marco up"
		}
	],
	"no_antialiasing": false,
	"image": "characters/Marco Phase 3",
	"position": [
		-10,
		-50
	],
	"healthicon": "marcophase3",
	"flip_x": false,
	"healthbar_colors": [
		34,
		34,
		34
	],
	"camera_position": [
		-140,
		-150
	],
	"sing_duration": 6.1,
	"scale": 1.2
}