<?xml version="1.0" encoding="UTF-8"?>
<!--
Created with Funkin Packer v0.1.3 https://neeeoo.github.io/funkin-packer/
-->
<TextureAtlas imagePath="GFWav.png" width="8160" height="4033">
	<SubTexture name="gf dodge0000" x="4272" y="1842" width="661" height="683" frameX="-151" frameY="-102" frameWidth="913" frameHeight="802"/>
	<SubTexture name="gf dodge0001" x="1667" y="2420" width="687" height="697" frameX="-130" frameY="-88" frameWidth="913" frameHeight="802"/>
	<SubTexture name="gf dodge0002" x="2916" y="2438" width="710" height="709" frameX="-112" frameY="-76" frameWidth="913" frameHeight="802"/>
	<SubTexture name="gf dodge0003" x="4131" y="2528" width="727" height="719" frameX="-98" frameY="-66" frameWidth="913" frameHeight="802"/>
	<SubTexture name="gf dodge0004" x="4861" y="2537" width="742" height="727" frameX="-86" frameY="-58" frameWidth="913" frameHeight="802"/>
	<SubTexture name="gf dodge0005" x="5606" y="2682" width="754" height="733" frameX="-76" frameY="-52" frameWidth="913" frameHeight="802"/>
	<SubTexture name="gf dodge0006" x="6865" y="2782" width="763" height="738" frameX="-69" frameY="-47" frameWidth="913" frameHeight="802"/>
	<SubTexture name="gf dodge0007" x="1" y="2992" width="770" height="742" frameX="-64" frameY="-43" frameWidth="913" frameHeight="802"/>
	<SubTexture name="gf dodge0008" x="774" y="3113" width="774" height="745" frameX="-60" frameY="-40" frameWidth="913" frameHeight="802"/>
	<SubTexture name="gf dodge0009" x="1551" y="3120" width="777" height="747" frameX="-57" frameY="-38" frameWidth="913" frameHeight="802"/>
	<SubTexture name="gf dodge0010" x="2833" y="3150" width="780" height="748" frameX="-55" frameY="-37" frameWidth="913" frameHeight="802"/>
	<SubTexture name="gf dodge0011" x="5554" y="1198" width="366" height="650" frameX="-361" frameY="-135" frameWidth="913" frameHeight="802"/>
	<SubTexture name="gf dodge0012" x="5554" y="1198" width="366" height="650" frameX="-360" frameY="-134" frameWidth="913" frameHeight="802"/>
	<SubTexture name="gf dodge0013" x="5554" y="1198" width="366" height="650" frameX="-360" frameY="-134" frameWidth="913" frameHeight="802"/>
	<SubTexture name="gf dodge0014" x="5554" y="1198" width="366" height="650" frameX="-360" frameY="-134" frameWidth="913" frameHeight="802"/>
	<SubTexture name="gf dodge0015" x="5554" y="1198" width="366" height="650" frameX="-360" frameY="-133" frameWidth="913" frameHeight="802"/>
	<SubTexture name="gf dodge0016" x="5554" y="1198" width="366" height="650" frameX="-360" frameY="-133" frameWidth="913" frameHeight="802"/>
	<SubTexture name="gf dodge0017" x="5554" y="1198" width="366" height="650" frameX="-360" frameY="-133" frameWidth="913" frameHeight="802"/>
	<SubTexture name="gf dodge0018" x="5554" y="1198" width="366" height="650" frameX="-360" frameY="-133" frameWidth="913" frameHeight="802"/>
	<SubTexture name="gf dodge0019" x="5554" y="1198" width="366" height="650" frameX="-360" frameY="-133" frameWidth="913" frameHeight="802"/>
	<SubTexture name="gf down0000" x="7262" y="796" width="476" height="552" frameX="-23" frameY="-42" frameWidth="529" frameHeight="604"/>
	<SubTexture name="gf down0001" x="475" y="1074" width="474" height="557" frameX="-25" frameY="-37" frameWidth="529" frameHeight="604"/>
	<SubTexture name="gf down0002" x="952" y="1085" width="473" height="557" frameX="-28" frameY="-37" frameWidth="529" frameHeight="604"/>
	<SubTexture name="gf down0003" x="1428" y="1085" width="473" height="558" frameX="-29" frameY="-36" frameWidth="529" frameHeight="604"/>
	<SubTexture name="gf down0004" x="1" y="1062" width="471" height="556" frameX="-28" frameY="-38" frameWidth="529" frameHeight="604"/>
	<SubTexture name="gf down0005" x="6788" y="796" width="471" height="544" frameX="-26" frameY="-50" frameWidth="529" frameHeight="604"/>
	<SubTexture name="gf down0006" x="6313" y="796" width="472" height="543" frameX="-26" frameY="-51" frameWidth="529" frameHeight="604"/>
	<SubTexture name="gf down0007" x="6313" y="796" width="472" height="543" frameX="-26" frameY="-51" frameWidth="529" frameHeight="604"/>
	<SubTexture name="gf first retry0000" x="1" y="1" width="1" height="1" frameX="-0" frameY="-0" frameWidth="716" frameHeight="310"/>
	<SubTexture name="gf first retry0001" x="1" y="1" width="1" height="1" frameX="-0" frameY="-0" frameWidth="716" frameHeight="310"/>
	<SubTexture name="gf first retry0002" x="1" y="1" width="1" height="1" frameX="-0" frameY="-0" frameWidth="716" frameHeight="310"/>
	<SubTexture name="gf first retry0003" x="1" y="1" width="1" height="1" frameX="-0" frameY="-0" frameWidth="716" frameHeight="310"/>
	<SubTexture name="gf first retry0004" x="1" y="1" width="1" height="1" frameX="-0" frameY="-0" frameWidth="716" frameHeight="310"/>
	<SubTexture name="gf first retry0005" x="1" y="1" width="1" height="1" frameX="-0" frameY="-0" frameWidth="716" frameHeight="310"/>
	<SubTexture name="gf first retry0006" x="1" y="1" width="1" height="1" frameX="-0" frameY="-0" frameWidth="716" frameHeight="310"/>
	<SubTexture name="gf first retry0007" x="1" y="1" width="1" height="1" frameX="-0" frameY="-0" frameWidth="716" frameHeight="310"/>
	<SubTexture name="gf first retry0008" x="1" y="1" width="1" height="1" frameX="-0" frameY="-0" frameWidth="716" frameHeight="310"/>
	<SubTexture name="gf first retry0009" x="1" y="1" width="1" height="1" frameX="-0" frameY="-0" frameWidth="716" frameHeight="310"/>
	<SubTexture name="gf first retry0010" x="1" y="1" width="1" height="1" frameX="-0" frameY="-0" frameWidth="716" frameHeight="310"/>
	<SubTexture name="gf first retry0011" x="1" y="1" width="1" height="1" frameX="-0" frameY="-0" frameWidth="716" frameHeight="310"/>
	<SubTexture name="gf first retry0012" x="5" y="1" width="655" height="261" frameX="-15" frameY="-28" frameWidth="716" frameHeight="310"/>
	<SubTexture name="gf first retry0013" x="663" y="1" width="656" height="261" frameX="-14" frameY="-28" frameWidth="716" frameHeight="310"/>
	<SubTexture name="gf first retry0014" x="1322" y="1" width="656" height="261" frameX="-14" frameY="-28" frameWidth="716" frameHeight="310"/>
	<SubTexture name="gf first retry0015" x="1981" y="1" width="657" height="262" frameX="-14" frameY="-27" frameWidth="716" frameHeight="310"/>
	<SubTexture name="gf first retry0016" x="2641" y="1" width="657" height="262" frameX="-14" frameY="-27" frameWidth="716" frameHeight="310"/>
	<SubTexture name="gf first retry0017" x="3301" y="1" width="657" height="262" frameX="-14" frameY="-27" frameWidth="716" frameHeight="310"/>
	<SubTexture name="gf first retry0018" x="3961" y="1" width="657" height="262" frameX="-14" frameY="-27" frameWidth="716" frameHeight="310"/>
	<SubTexture name="gf first retry0019" x="4621" y="1" width="657" height="262" frameX="-14" frameY="-27" frameWidth="716" frameHeight="310"/>
	<SubTexture name="gf first retry0020" x="5281" y="1" width="657" height="262" frameX="-14" frameY="-27" frameWidth="716" frameHeight="310"/>
	<SubTexture name="gf first retry0021" x="5941" y="1" width="658" height="262" frameX="-13" frameY="-27" frameWidth="716" frameHeight="310"/>
	<SubTexture name="gf first retry0022" x="6602" y="1" width="658" height="262" frameX="-13" frameY="-27" frameWidth="716" frameHeight="310"/>
	<SubTexture name="gf first retry0023" x="7263" y="1" width="658" height="262" frameX="-13" frameY="-27" frameWidth="716" frameHeight="310"/>
	<SubTexture name="gf first retry0024" x="1" y="265" width="658" height="262" frameX="-13" frameY="-27" frameWidth="716" frameHeight="310"/>
	<SubTexture name="gf first retry0025" x="662" y="265" width="658" height="262" frameX="-13" frameY="-27" frameWidth="716" frameHeight="310"/>
	<SubTexture name="gf first retry0026" x="1323" y="266" width="658" height="262" frameX="-13" frameY="-27" frameWidth="716" frameHeight="310"/>
	<SubTexture name="gf first retry0027" x="1984" y="266" width="658" height="262" frameX="-13" frameY="-27" frameWidth="716" frameHeight="310"/>
	<SubTexture name="gf first retry0028" x="2645" y="266" width="658" height="262" frameX="-13" frameY="-27" frameWidth="716" frameHeight="310"/>
	<SubTexture name="gf first retry0029" x="3306" y="266" width="658" height="262" frameX="-13" frameY="-27" frameWidth="716" frameHeight="310"/>
	<SubTexture name="gf first retry0030" x="3967" y="266" width="658" height="262" frameX="-13" frameY="-27" frameWidth="716" frameHeight="310"/>
	<SubTexture name="gf first retry0031" x="4628" y="266" width="658" height="262" frameX="-13" frameY="-27" frameWidth="716" frameHeight="310"/>
	<SubTexture name="gf first retry0032" x="5289" y="266" width="658" height="262" frameX="-13" frameY="-27" frameWidth="716" frameHeight="310"/>
	<SubTexture name="gf first retry0033" x="5950" y="266" width="658" height="262" frameX="-13" frameY="-27" frameWidth="716" frameHeight="310"/>
	<SubTexture name="gf first retry0034" x="6611" y="266" width="658" height="262" frameX="-13" frameY="-27" frameWidth="716" frameHeight="310"/>
	<SubTexture name="gf first retry0035" x="7272" y="266" width="658" height="262" frameX="-13" frameY="-27" frameWidth="716" frameHeight="310"/>
	<SubTexture name="gf first retry0036" x="1" y="530" width="658" height="262" frameX="-13" frameY="-27" frameWidth="716" frameHeight="310"/>
	<SubTexture name="gf first retry0037" x="662" y="530" width="658" height="262" frameX="-13" frameY="-27" frameWidth="716" frameHeight="310"/>
	<SubTexture name="gf first retry0038" x="1323" y="531" width="658" height="262" frameX="-13" frameY="-27" frameWidth="716" frameHeight="310"/>
	<SubTexture name="gf first retry0039" x="1984" y="531" width="658" height="262" frameX="-13" frameY="-27" frameWidth="716" frameHeight="310"/>
	<SubTexture name="gf first retry0040" x="2645" y="531" width="658" height="262" frameX="-13" frameY="-27" frameWidth="716" frameHeight="310"/>
	<SubTexture name="gf first retry0041" x="3306" y="531" width="658" height="262" frameX="-13" frameY="-27" frameWidth="716" frameHeight="310"/>
	<SubTexture name="gf first retry0042" x="3967" y="531" width="658" height="262" frameX="-13" frameY="-27" frameWidth="716" frameHeight="310"/>
	<SubTexture name="gf first retry0043" x="4628" y="531" width="658" height="262" frameX="-13" frameY="-27" frameWidth="716" frameHeight="310"/>
	<SubTexture name="gf first retry0044" x="5289" y="531" width="658" height="262" frameX="-13" frameY="-27" frameWidth="716" frameHeight="310"/>
	<SubTexture name="gf first retry0045" x="5950" y="531" width="658" height="262" frameX="-13" frameY="-27" frameWidth="716" frameHeight="310"/>
	<SubTexture name="gf first retry0046" x="6611" y="531" width="658" height="262" frameX="-13" frameY="-27" frameWidth="716" frameHeight="310"/>
	<SubTexture name="gf first retry0047" x="7272" y="531" width="658" height="262" frameX="-13" frameY="-27" frameWidth="716" frameHeight="310"/>
	<SubTexture name="gf first retry0048" x="7272" y="531" width="658" height="262" frameX="-13" frameY="-27" frameWidth="716" frameHeight="310"/>
	<SubTexture name="gf first retry0049" x="7272" y="531" width="658" height="262" frameX="-13" frameY="-27" frameWidth="716" frameHeight="310"/>
	<SubTexture name="gf first retry0050" x="7272" y="531" width="658" height="262" frameX="-13" frameY="-27" frameWidth="716" frameHeight="310"/>
	<SubTexture name="gf first retry0051" x="7272" y="531" width="658" height="262" frameX="-13" frameY="-27" frameWidth="716" frameHeight="310"/>
	<SubTexture name="gf first retry0052" x="7272" y="531" width="658" height="262" frameX="-13" frameY="-27" frameWidth="716" frameHeight="310"/>
	<SubTexture name="gf first retry0053" x="7272" y="531" width="658" height="262" frameX="-13" frameY="-27" frameWidth="716" frameHeight="310"/>
	<SubTexture name="gf first retry0054" x="7272" y="531" width="658" height="262" frameX="-13" frameY="-27" frameWidth="716" frameHeight="310"/>
	<SubTexture name="gf first retry0055" x="7272" y="531" width="658" height="262" frameX="-13" frameY="-27" frameWidth="716" frameHeight="310"/>
	<SubTexture name="gf first retry0056" x="7272" y="531" width="658" height="262" frameX="-13" frameY="-27" frameWidth="716" frameHeight="310"/>
	<SubTexture name="gf first retry0057" x="7272" y="531" width="658" height="262" frameX="-13" frameY="-27" frameWidth="716" frameHeight="310"/>
	<SubTexture name="gf first retry0058" x="7272" y="531" width="658" height="262" frameX="-13" frameY="-27" frameWidth="716" frameHeight="310"/>
	<SubTexture name="gf first retry0059" x="7272" y="531" width="658" height="262" frameX="-13" frameY="-27" frameWidth="716" frameHeight="310"/>
	<SubTexture name="gf idle0000" x="5923" y="1198" width="366" height="650" frameX="-45" frameY="-12" frameWidth="440" frameHeight="670"/>
	<SubTexture name="gf idle0001" x="3702" y="1105" width="368" height="647" frameX="-41" frameY="-15" frameWidth="440" frameHeight="670"/>
	<SubTexture name="gf idle0002" x="3333" y="1105" width="366" height="643" frameX="-36" frameY="-19" frameWidth="440" frameHeight="670"/>
	<SubTexture name="gf idle0003" x="1904" y="1094" width="354" height="639" frameX="-34" frameY="-23" frameWidth="440" frameHeight="670"/>
	<SubTexture name="gf idle0004" x="2261" y="1094" width="352" height="639" frameX="-34" frameY="-23" frameWidth="440" frameHeight="670"/>
	<SubTexture name="gf idle0005" x="2261" y="1094" width="352" height="639" frameX="-34" frameY="-23" frameWidth="440" frameHeight="670"/>
	<SubTexture name="gf idle0006" x="2616" y="1102" width="354" height="639" frameX="-34" frameY="-23" frameWidth="440" frameHeight="670"/>
	<SubTexture name="gf idle0007" x="2973" y="1102" width="357" height="641" frameX="-37" frameY="-21" frameWidth="440" frameHeight="670"/>
	<SubTexture name="gf idle0008" x="5923" y="1198" width="366" height="650" frameX="-45" frameY="-12" frameWidth="440" frameHeight="670"/>
	<SubTexture name="gf idle0009" x="1" y="1621" width="370" height="651" frameX="-46" frameY="-11" frameWidth="440" frameHeight="670"/>
	<SubTexture name="gf idle0010" x="374" y="1634" width="370" height="651" frameX="-47" frameY="-11" frameWidth="440" frameHeight="670"/>
	<SubTexture name="gf idle0011" x="374" y="1634" width="370" height="651" frameX="-47" frameY="-11" frameWidth="440" frameHeight="670"/>
	<SubTexture name="gf idle0012" x="747" y="1645" width="369" height="651" frameX="-47" frameY="-11" frameWidth="440" frameHeight="670"/>
	<SubTexture name="gf idle0013" x="6292" y="1342" width="367" height="650" frameX="-47" frameY="-12" frameWidth="440" frameHeight="670"/>
	<SubTexture name="gf idle0014" x="6662" y="1343" width="368" height="650" frameX="-46" frameY="-12" frameWidth="440" frameHeight="670"/>
	<SubTexture name="gf left0000" x="2071" y="1736" width="540" height="681" frameX="-45" frameY="-15" frameWidth="615" frameHeight="705"/>
	<SubTexture name="gf left0001" x="4936" y="1842" width="551" height="683" frameX="-34" frameY="-13" frameWidth="615" frameHeight="705"/>
	<SubTexture name="gf left0002" x="6040" y="1995" width="548" height="684" frameX="-37" frameY="-13" frameWidth="615" frameHeight="705"/>
	<SubTexture name="gf left0003" x="5490" y="1851" width="547" height="683" frameX="-38" frameY="-14" frameWidth="615" frameHeight="705"/>
	<SubTexture name="gf left0004" x="1521" y="1736" width="547" height="680" frameX="-38" frameY="-17" frameWidth="615" frameHeight="705"/>
	<SubTexture name="gf left0005" x="2614" y="1746" width="547" height="680" frameX="-38" frameY="-17" frameWidth="615" frameHeight="705"/>
	<SubTexture name="gf left0006" x="3164" y="1755" width="547" height="680" frameX="-38" frameY="-17" frameWidth="615" frameHeight="705"/>
	<SubTexture name="gf left0007" x="3164" y="1755" width="547" height="680" frameX="-38" frameY="-17" frameWidth="615" frameHeight="705"/>
	<SubTexture name="gf miss0000" x="4204" y="796" width="431" height="361" frameX="-39" frameY="-33" frameWidth="497" frameHeight="426"/>
	<SubTexture name="gf miss0001" x="4204" y="796" width="431" height="361" frameX="-39" frameY="-33" frameWidth="497" frameHeight="426"/>
	<SubTexture name="gf miss0002" x="4204" y="796" width="431" height="361" frameX="-39" frameY="-33" frameWidth="497" frameHeight="426"/>
	<SubTexture name="gf miss0003" x="4204" y="796" width="431" height="361" frameX="-39" frameY="-33" frameWidth="497" frameHeight="426"/>
	<SubTexture name="gf miss0004" x="4204" y="796" width="431" height="361" frameX="-39" frameY="-33" frameWidth="497" frameHeight="426"/>
	<SubTexture name="gf miss0005" x="4204" y="796" width="431" height="361" frameX="-39" frameY="-33" frameWidth="497" frameHeight="426"/>
	<SubTexture name="gf miss0006" x="4204" y="796" width="431" height="361" frameX="-39" frameY="-33" frameWidth="497" frameHeight="426"/>
	<SubTexture name="gf miss0007" x="4204" y="796" width="431" height="361" frameX="-39" frameY="-33" frameWidth="497" frameHeight="426"/>
	<SubTexture name="gf miss0008" x="4204" y="796" width="431" height="361" frameX="-39" frameY="-33" frameWidth="497" frameHeight="426"/>
	<SubTexture name="gf miss0009" x="4204" y="796" width="431" height="361" frameX="-39" frameY="-33" frameWidth="497" frameHeight="426"/>
	<SubTexture name="gf retry0000" x="1" y="795" width="660" height="264" frameX="-50" frameY="-53" frameWidth="793" frameHeight="363"/>
	<SubTexture name="gf retry0001" x="664" y="796" width="676" height="275" frameX="-42" frameY="-47" frameWidth="793" frameHeight="363"/>
	<SubTexture name="gf retry0002" x="1343" y="796" width="694" height="286" frameX="-33" frameY="-41" frameWidth="793" frameHeight="363"/>
	<SubTexture name="gf retry0003" x="2040" y="796" width="709" height="295" frameX="-25" frameY="-37" frameWidth="793" frameHeight="363"/>
	<SubTexture name="gf retry0004" x="2752" y="796" width="720" height="303" frameX="-19" frameY="-33" frameWidth="793" frameHeight="363"/>
	<SubTexture name="gf retry0005" x="3475" y="796" width="726" height="306" frameX="-16" frameY="-32" frameWidth="793" frameHeight="363"/>
	<SubTexture name="gf retry0006" x="7272" y="531" width="658" height="262" frameX="-13" frameY="-27" frameWidth="793" frameHeight="363"/>
	<SubTexture name="gf retry0007" x="7272" y="531" width="658" height="262" frameX="-13" frameY="-27" frameWidth="793" frameHeight="363"/>
	<SubTexture name="gf retry0008" x="7272" y="531" width="658" height="262" frameX="-13" frameY="-27" frameWidth="793" frameHeight="363"/>
	<SubTexture name="gf retry0009" x="7272" y="531" width="658" height="262" frameX="-13" frameY="-27" frameWidth="793" frameHeight="363"/>
	<SubTexture name="gf retry0010" x="7272" y="531" width="658" height="262" frameX="-13" frameY="-27" frameWidth="793" frameHeight="363"/>
	<SubTexture name="gf retry0011" x="7272" y="531" width="658" height="262" frameX="-13" frameY="-27" frameWidth="793" frameHeight="363"/>
	<SubTexture name="gf right0000" x="1" y="2288" width="552" height="690" frameX="-26" frameY="-23" frameWidth="604" frameHeight="725"/>
	<SubTexture name="gf right0001" x="556" y="2299" width="552" height="690" frameX="-36" frameY="-23" frameWidth="604" frameHeight="725"/>
	<SubTexture name="gf right0002" x="1111" y="2419" width="553" height="691" frameX="-32" frameY="-22" frameWidth="604" frameHeight="725"/>
	<SubTexture name="gf right0003" x="2357" y="2429" width="556" height="699" frameX="-29" frameY="-14" frameWidth="604" frameHeight="725"/>
	<SubTexture name="gf right0004" x="3714" y="1811" width="555" height="680" frameX="-29" frameY="-33" frameWidth="604" frameHeight="725"/>
	<SubTexture name="gf right0005" x="5755" y="796" width="555" height="399" frameX="-29" frameY="-314" frameWidth="604" frameHeight="725"/>
	<SubTexture name="gf right0006" x="4638" y="796" width="556" height="391" frameX="-29" frameY="-322" frameWidth="604" frameHeight="725"/>
	<SubTexture name="gf right0007" x="5197" y="796" width="555" height="391" frameX="-29" frameY="-322" frameWidth="604" frameHeight="725"/>
	<SubTexture name="gf right0008" x="5197" y="796" width="555" height="391" frameX="-29" frameY="-322" frameWidth="604" frameHeight="725"/>
	<SubTexture name="gf right0009" x="5197" y="796" width="555" height="391" frameX="-29" frameY="-322" frameWidth="604" frameHeight="725"/>
	<SubTexture name="gf up0000" x="3629" y="2494" width="499" height="746" frameX="-10" frameY="-48" frameWidth="539" frameHeight="805"/>
	<SubTexture name="gf up0001" x="2331" y="3131" width="499" height="761" frameX="-10" frameY="-33" frameWidth="539" frameHeight="805"/>
	<SubTexture name="gf up0002" x="4118" y="3250" width="499" height="765" frameX="-10" frameY="-30" frameWidth="539" frameHeight="805"/>
	<SubTexture name="gf up0003" x="4620" y="3267" width="499" height="765" frameX="-10" frameY="-30" frameWidth="539" frameHeight="805"/>
	<SubTexture name="gf up0004" x="3616" y="3243" width="499" height="762" frameX="-10" frameY="-32" frameWidth="539" frameHeight="805"/>
	<SubTexture name="gf up0005" x="7631" y="2782" width="499" height="752" frameX="-10" frameY="-42" frameWidth="539" frameHeight="805"/>
	<SubTexture name="gf up0006" x="6363" y="2683" width="499" height="751" frameX="-10" frameY="-43" frameWidth="539" frameHeight="805"/>
	<SubTexture name="gf up0007" x="6363" y="2683" width="499" height="751" frameX="-10" frameY="-43" frameWidth="539" frameHeight="805"/>
	<SubTexture name="gf vpose0000" x="7033" y="1351" width="376" height="650" frameX="-10" frameY="-65" frameWidth="499" frameHeight="723"/>
	<SubTexture name="gf vpose0001" x="7741" y="796" width="353" height="638" frameX="-22" frameY="-77" frameWidth="499" frameHeight="723"/>
	<SubTexture name="gf vpose0002" x="4073" y="1160" width="364" height="648" frameX="-32" frameY="-67" frameWidth="499" frameHeight="723"/>
	<SubTexture name="gf vpose0003" x="7006" y="2090" width="414" height="685" frameX="-37" frameY="-30" frameWidth="499" frameHeight="723"/>
	<SubTexture name="gf vpose0004" x="7423" y="2090" width="414" height="689" frameX="-38" frameY="-26" frameWidth="499" frameHeight="723"/>
	<SubTexture name="gf vpose0005" x="6591" y="1996" width="412" height="684" frameX="-38" frameY="-31" frameWidth="499" frameHeight="723"/>
	<SubTexture name="gf vpose0006" x="1119" y="1646" width="399" height="665" frameX="-38" frameY="-50" frameWidth="499" frameHeight="723"/>
	<SubTexture name="gf vpose0007" x="7412" y="1437" width="372" height="650" frameX="-38" frameY="-65" frameWidth="499" frameHeight="723"/>
	<SubTexture name="gf vpose0008" x="4810" y="1190" width="368" height="649" frameX="-38" frameY="-66" frameWidth="499" frameHeight="723"/>
	<SubTexture name="gf vpose0009" x="4440" y="1190" width="367" height="648" frameX="-38" frameY="-67" frameWidth="499" frameHeight="723"/>
	<SubTexture name="gf vpose0010" x="5181" y="1190" width="370" height="649" frameX="-38" frameY="-66" frameWidth="499" frameHeight="723"/>
	<SubTexture name="gf vpose0011" x="7787" y="1437" width="372" height="650" frameX="-38" frameY="-65" frameWidth="499" frameHeight="723"/>
	<SubTexture name="gf vpose0012" x="7787" y="1437" width="372" height="650" frameX="-38" frameY="-65" frameWidth="499" frameHeight="723"/>
	<SubTexture name="gf vpose0013" x="7787" y="1437" width="372" height="650" frameX="-38" frameY="-65" frameWidth="499" frameHeight="723"/>
	<SubTexture name="gf vpose0014" x="7787" y="1437" width="372" height="650" frameX="-38" frameY="-65" frameWidth="499" frameHeight="723"/>
</TextureAtlas>